contributing/README.md
contributing/requirements.txt
examples/create_dataset.py
examples/create_dataset_object.py
examples/create_image_task.py
examples/delete_dataset.py
examples/delete_dataset_object.py
examples/download_dataset_objects.py
examples/download_images.py
examples/execute_auto_annotation_job.py
examples/export_coco.py
examples/export_yolo.py
examples/find_dataset.py
examples/find_dataset_object.py
examples/get_auto_annotation_jobs.py
examples/get_dataset_objects.py
examples/get_datasets.py
examples/get_metadatas.py
examples/import_yolo.py
examples/update_dataset.py
examples/update_dataset_object.py
fastlabel/__init__.py
fastlabel/api.py
fastlabel/const.py
fastlabel/converters.py
fastlabel/exceptions.py
fastlabel/query.py
fastlabel/utils/__init__.py
fastlabel/utils/mask_image_util.py
tests/test_converters.py
fastlabel-0.19.10.dist-info/LICENSE
fastlabel-0.19.10.dist-info/METADATA
fastlabel-0.19.10.dist-info/WHEEL
fastlabel-0.19.10.dist-info/top_level.txt
fastlabel-0.19.10.dist-info/RECORD
