Metadata-Version: 2.1
Name: fastlabel
Version: 0.19.10
Summary: The official Python SDK for FastLabel API, the Data Platform for AI
Author-email: eisuke-ueta <eisuke.ueta@fastlabel.ai>
Requires-Python: >=3.8
License-File: LICENSE
Requires-Dist: requests<3.0,>=2.4.2
Requires-Dist: numpy<2.0.0,>=1.26.0
Requires-Dist: geojson<4.0,>=2.0.0
Requires-Dist: xmltodict==0.12.0
Requires-Dist: Pillow<11.0.0,>=10.0.0
Requires-Dist: opencv-python<5.0.0,>=4.0.0
Requires-Dist: aiohttp>=3.8.5
